<?xml version="1.0" encoding="utf-8"?>
<androidx.constraintlayout.widget.ConstraintLayout xmlns:android="http://schemas.android.com/apk/res/android"
    xmlns:app="http://schemas.android.com/apk/res-auto"
    xmlns:tools="http://schemas.android.com/tools"
    android:id="@+id/main"
    android:layout_width="match_parent"
    android:layout_height="match_parent"
    tools:context=".MainActivity">

    <LinearLayout
        android:layout_width="409dp"
        android:layout_height="729dp"
        android:orientation="vertical"
        tools:layout_editor_absoluteX="1dp"
        tools:layout_editor_absoluteY="1dp">

        <ImageView
            android:layout_marginTop="50dp"
            android:id="@+id/imageView"
            android:layout_width="match_parent"
            android:layout_height="wrap_content"
            app:srcCompat="@drawable/ahha" />

        <LinearLayout
            android:layout_marginRight="20dp"
            android:layout_marginLeft="20dp"
            android:layout_marginTop="40dp"
            android:layout_width="match_parent"
            android:layout_height="50dp"
            android:orientation="horizontal">

            <TextView
                android:id="@+id/textView"
                android:layout_width="wrap_content"
                android:layout_height="50dp"
                android:layout_weight="1"
                android:paddingLeft="20dp"
                android:text="이름" />

            <EditText
                android:layout_width="wrap_content"
                android:layout_height="50dp"
                android:layout_weight="5"
                android:hint="Name"></EditText>
        </LinearLayout>

        <LinearLayout
            android:layout_width="match_parent"
            android:layout_height="50dp"
            android:orientation="horizontal"
            android:layout_marginRight="20dp"
            android:layout_marginLeft="20dp"
            android:layout_marginTop="10dp"
            >

            <TextView
                android:id="@+id/textview2"
                android:layout_width="wrap_content"
                android:layout_height="50dp"
                android:layout_weight="1"
                android:text="비밀번호"></TextView>
            <EditText
                android:id="@+id/editText2"
                android:layout_width="wrap_content"
                android:layout_height="50dp"
                android:layout_weight="5"
                android:hint="password"
                android:inputType="textPassword"
                ></EditText>
        </LinearLayout>

        <LinearLayout
            android:layout_width="wrap_content"
            android:layout_height="70dp"
            android:orientation="horizontal"
            android:paddingLeft="20dp"
            android:layout_gravity="center_horizontal"

            android:paddingTop="20dp"
            android:paddingRight="20dp">

            <Button
                android:layout_width="wrap_content"
                android:layout_height="50dp"
                android:layout_gravity="left"
                android:layout_marginRight="50dp"
                android:text="로그인"></Button>

            <Button
                android:layout_width="wrap_content"
                android:layout_height="50dp"
                android:text="회원가입"></Button>
        </LinearLayout>
        <TextView
            android:layout_marginTop="20dp"
            android:layout_gravity="center"
            android:layout_width="350dp"
            android:layout_height="150dp"
            android:hint="입력할 내용을 여기에 표시하시오."

    </LinearLayout>
</androidx.constraintlayout.widget.ConstraintLayout>